mymulti_key_dict/README.MD
mymulti_key_dict/__init__.py
mymulti_key_dict/requirements.txt
mymulti_key_dict/thirdparty.json
mymulti_key_dict-0.15.dist-info/LICENSE.rst
mymulti_key_dict-0.15.dist-info/METADATA
mymulti_key_dict-0.15.dist-info/WHEEL
mymulti_key_dict-0.15.dist-info/top_level.txt
mymulti_key_dict-0.15.dist-info/RECORD
