Metadata-Version: 2.1
Name: mymulti_key_dict
Version: 0.15
Summary: Access nested dict elements as d[[1,2,3]] instead of d[1][2][3] - compatible with dict() - no requirements
Home-page: https://github.com/hansalemaos/mymulti_key_dict
Author: Johannes Fischer
Author-email: aulasparticularesdealemaosp@gmail.com
License: MIT
Keywords: nested,dicts
Classifier: Development Status :: 4 - Beta
Classifier: Programming Language :: Python :: 3 :: Only
Classifier: Programming Language :: Python :: 3.10
Classifier: Topic :: Software Development :: Libraries :: Python Modules
Classifier: Topic :: Utilities
License-File: LICENSE.rst
